fast_plate_ocr/__init__.py
fast_plate_ocr/py.typed
fast_plate_ocr/cli/__init__.py
fast_plate_ocr/cli/cli.py
fast_plate_ocr/cli/dataset_stats.py
fast_plate_ocr/cli/export.py
fast_plate_ocr/cli/train.py
fast_plate_ocr/cli/utils.py
fast_plate_ocr/cli/valid.py
fast_plate_ocr/cli/validate_dataset.py
fast_plate_ocr/cli/visualize_augmentation.py
fast_plate_ocr/cli/visualize_predictions.py
fast_plate_ocr/core/__init__.py
fast_plate_ocr/core/process.py
fast_plate_ocr/core/types.py
fast_plate_ocr/core/utils.py
fast_plate_ocr/inference/__init__.py
fast_plate_ocr/inference/config.py
fast_plate_ocr/inference/hub.py
fast_plate_ocr/inference/plate_recognizer.py
fast_plate_ocr/train/__init__.py
fast_plate_ocr/train/data/__init__.py
fast_plate_ocr/train/data/augmentation.py
fast_plate_ocr/train/data/dataset.py
fast_plate_ocr/train/model/__init__.py
fast_plate_ocr/train/model/config.py
fast_plate_ocr/train/model/layers.py
fast_plate_ocr/train/model/loss.py
fast_plate_ocr/train/model/metric.py
fast_plate_ocr/train/model/model_builders.py
fast_plate_ocr/train/model/model_schema.py
fast_plate_ocr/train/utilities/__init__.py
fast_plate_ocr/train/utilities/backend_utils.py
fast_plate_ocr/train/utilities/utils.py
fast_plate_ocr-1.0.2.dist-info/METADATA
fast_plate_ocr-1.0.2.dist-info/WHEEL
fast_plate_ocr-1.0.2.dist-info/entry_points.txt
fast_plate_ocr-1.0.2.dist-info/licenses/LICENSE
fast_plate_ocr-1.0.2.dist-info/RECORD
