Metadata-Version: 2.4
Name: fast-plate-ocr
Version: 1.0.2
Summary: Fast & Lightweight OCR for vehicle license plates.
Project-URL: Repository, https://github.com/ankandrew/fast-plate-ocr/
Project-URL: Documentation, https://ankandrew.github.io/fast-plate-ocr
Author-email: ankandrew <61120139+ankandrew@users.noreply.github.com>
License-Expression: MIT
License-File: LICENSE
Keywords: license-plate-ocr,license-plate-recognition,plate-recognition
Classifier: Intended Audience :: Developers
Classifier: Intended Audience :: Education
Classifier: Intended Audience :: Science/Research
Classifier: Operating System :: OS Independent
Classifier: Programming Language :: Python :: 3
Classifier: Programming Language :: Python :: 3 :: Only
Classifier: Programming Language :: Python :: 3.10
Classifier: Programming Language :: Python :: 3.11
Classifier: Programming Language :: Python :: 3.12
Classifier: Programming Language :: Python :: 3.13
Classifier: Topic :: Scientific/Engineering
Classifier: Topic :: Scientific/Engineering :: Artificial Intelligence
Classifier: Topic :: Software Development
Classifier: Topic :: Software Development :: Build Tools
Classifier: Topic :: Software Development :: Libraries
Classifier: Topic :: Software Development :: Libraries :: Python Modules
Classifier: Typing :: Typed
Requires-Python: >=3.10
Requires-Dist: numpy>=1.20
Requires-Dist: opencv-python-headless
Requires-Dist: pyyaml>=5.1
Requires-Dist: rich
Requires-Dist: tqdm
Provides-Extra: onnx
Requires-Dist: onnxruntime; extra == 'onnx'
Provides-Extra: onnx-directml
Requires-Dist: onnxruntime-directml; extra == 'onnx-directml'
Provides-Extra: onnx-gpu
Requires-Dist: onnxruntime-gpu; extra == 'onnx-gpu'
Provides-Extra: onnx-openvino
Requires-Dist: onnxruntime-openvino; extra == 'onnx-openvino'
Provides-Extra: onnx-qnn
Requires-Dist: onnxruntime-qnn; extra == 'onnx-qnn'
Provides-Extra: train
Requires-Dist: albumentations; extra == 'train'
Requires-Dist: click; extra == 'train'
Requires-Dist: coremltools; extra == 'train'
Requires-Dist: keras<4,>=3.10.0; extra == 'train'
Requires-Dist: matplotlib; extra == 'train'
Requires-Dist: onnxslim>=0.1.56; extra == 'train'
Requires-Dist: pandas; extra == 'train'
Requires-Dist: pydantic<3,>=2.5.2; extra == 'train'
Requires-Dist: scikit-learn; extra == 'train'
Requires-Dist: tensorboard; extra == 'train'
Requires-Dist: tensorflow; extra == 'train'
Requires-Dist: tf2onnx; extra == 'train'
